cliqa/__init__.py
cliqa/checks.py
cliqa/cli.py
cliqa/models.py
cliqa/runner.py
cliqa-0.1.4.dist-info/METADATA
cliqa-0.1.4.dist-info/WHEEL
cliqa-0.1.4.dist-info/entry_points.txt
cliqa-0.1.4.dist-info/licenses/LICENSE
cliqa-0.1.4.dist-info/RECORD
