Metadata-Version: 2.4
Name: cliqa
Version: 0.1.4
Summary: Analyze CLI tools against clig.dev guidelines
Project-URL: Homepage, https://github.com/benomahony/cliqa
Project-URL: Repository, https://github.com/benomahony/cliqa
Project-URL: Issues, https://github.com/benomahony/cliqa/issues
Author-email: Ben O'Mahony <benomahony@users.noreply.github.com>
License: MIT
License-File: LICENSE
Keywords: analysis,cli,clig,command-line,guidelines,linter
Classifier: Development Status :: 3 - Alpha
Classifier: Environment :: Console
Classifier: Intended Audience :: Developers
Classifier: License :: OSI Approved :: MIT License
Classifier: Programming Language :: Python :: 3
Classifier: Programming Language :: Python :: 3.12
Classifier: Programming Language :: Python :: 3.13
Classifier: Topic :: Software Development :: Quality Assurance
Classifier: Topic :: Software Development :: Testing
Requires-Python: >=3.12
Requires-Dist: pydantic-ai>=1.47.0
Requires-Dist: rich>=14.2.0
Requires-Dist: typer>=0.21.1
Provides-Extra: test
Requires-Dist: pytest-asyncio>=0.23.0; extra == 'test'
Requires-Dist: pytest-cov>=4.1.0; extra == 'test'
Requires-Dist: pytest>=8.0.0; extra == 'test'
